{
    "backend": "django",
    "db_name": "",
    "db_pass": "",
    "db_type": "mysql",
    "db_user": "",
    "dbms": "1",
    "description": "generated product",
    "design": "datta-able",
    "docker": "1",
    "err_code": 0,
    "frontend": "",
    "heroku": "0",
    "pattern": "mvc",
    "pro": "0",
    "task_id": "99adffdb-df23-4183-9bf8-e10cd3b8d864",
    "task_info": "Upload Sources [0%] - 166 files",
    "task_output": "99adffdb-df23-4183-9bf8-e10cd3b8d864.zip",
    "task_result": "SUCCESS",
    "task_state": "RUNNING",
    "task_ts_end": "2022-07-13-22-05-20",
    "task_ts_start": "2022-07-13-22-05-18"
}